setup.py
yulonglib/__init__.py
yulonglib/conf.py
yulonglib/diff.py
yulonglib/generator.py
yulonglib/getcookie.py
yulonglib/jseq.py
yulonglib/jsonseq.py
yulonglib/process_thread.py
yulonglib/sock.py
yulonglib/test.py
yulonglib/test_jseq.py
yulonglib/zpz.py
yulonglib.egg-info/PKG-INFO
yulonglib.egg-info/SOURCES.txt
yulonglib.egg-info/dependency_links.txt
yulonglib.egg-info/requires.txt
yulonglib.egg-info/top_level.txt