Metadata-Version: 1.0
Name: yulonglib
Version: 0.0.0.2
Summary: 功能齐全的jseq工具;功能齐全的conf工具;sock工具;多进线程工具
Home-page: http://pydison.github.io
Author: pydison
Author-email: pydison@gmail.com
License: UNKNOWN
Platform: UNKNOWN
